{
  "generatedAt": "2026-07-02T15:09:08+08:00",
  "entries": [
    {
      "rank": 1,
      "maskedName": "RES*** KA**",
      "totalBallots": 3
    },
    {
      "rank": 2,
      "maskedName": "DONO*** TA* WE* XU**",
      "totalBallots": 2
    },
    {
      "rank": 3,
      "maskedName": "GI** LO* Y* PI*",
      "totalBallots": 2
    },
    {
      "rank": 4,
      "maskedName": "JEW** SE* KA* LI*",
      "totalBallots": 2
    },
    {
      "rank": 5,
      "maskedName": "TA* BA* CH** JE**",
      "totalBallots": 2
    },
    {
      "rank": 6,
      "maskedName": "ADEL**** YE*",
      "totalBallots": 1
    },
    {
      "rank": 7,
      "maskedName": "ALL** CHO** CHU** JI*",
      "totalBallots": 1
    },
    {
      "rank": 8,
      "maskedName": "BRAN*** LI*",
      "totalBallots": 1
    },
    {
      "rank": 9,
      "maskedName": "BRE*** CHE**",
      "totalBallots": 1
    },
    {
      "rank": 10,
      "maskedName": "CH** YE** YE** AND***",
      "totalBallots": 1
    },
    {
      "rank": 11,
      "maskedName": "CHE*** JI* RO**",
      "totalBallots": 1
    },
    {
      "rank": 12,
      "maskedName": "CH** Y* HA* KENN***",
      "totalBallots": 1
    },
    {
      "rank": 13,
      "maskedName": "CH** WE* KI**",
      "totalBallots": 1
    },
    {
      "rank": 14,
      "maskedName": "DEN*** N*",
      "totalBallots": 1
    },
    {
      "rank": 15,
      "maskedName": "DI** JIAN***",
      "totalBallots": 1
    },
    {
      "rank": 16,
      "maskedName": "DIV*** VIM**",
      "totalBallots": 1
    },
    {
      "rank": 17,
      "maskedName": "ELL*** KO*",
      "totalBallots": 1
    },
    {
      "rank": 18,
      "maskedName": "ER** WO** KE* TH**",
      "totalBallots": 1
    },
    {
      "rank": 19,
      "maskedName": "EVE*** WO** PA* E*",
      "totalBallots": 1
    },
    {
      "rank": 20,
      "maskedName": "GU* ZI**",
      "totalBallots": 1
    },
    {
      "rank": 21,
      "maskedName": "HAN*** LO*",
      "totalBallots": 1
    },
    {
      "rank": 22,
      "maskedName": "HE** ZH* FE**",
      "totalBallots": 1
    },
    {
      "rank": 23,
      "maskedName": "HERL*** BT* DULK****",
      "totalBallots": 1
    },
    {
      "rank": 24,
      "maskedName": "H* SH** JI*",
      "totalBallots": 1
    },
    {
      "rank": 25,
      "maskedName": "HU* Y* NG**",
      "totalBallots": 1
    },
    {
      "rank": 26,
      "maskedName": "JAR*** CHO** WE* HU**",
      "totalBallots": 1
    },
    {
      "rank": 27,
      "maskedName": "JE** JAE***",
      "totalBallots": 1
    },
    {
      "rank": 28,
      "maskedName": "JOS*** HE** SIA** BO**",
      "totalBallots": 1
    },
    {
      "rank": 29,
      "maskedName": "KA* LI** SO**",
      "totalBallots": 1
    },
    {
      "rank": 30,
      "maskedName": "KEF** LI**",
      "totalBallots": 1
    },
    {
      "rank": 31,
      "maskedName": "LI* JU* HA*",
      "totalBallots": 1
    },
    {
      "rank": 32,
      "maskedName": "LIN** FO* MU* YE**",
      "totalBallots": 1
    },
    {
      "rank": 33,
      "maskedName": "LO* J* XI**",
      "totalBallots": 1
    },
    {
      "rank": 34,
      "maskedName": "L* JI* NI**",
      "totalBallots": 1
    },
    {
      "rank": 35,
      "maskedName": "MAL*** RA*",
      "totalBallots": 1
    },
    {
      "rank": 36,
      "maskedName": "MAUR*** LI*",
      "totalBallots": 1
    },
    {
      "rank": 37,
      "maskedName": "MOHA**** AZ** BI* ZAM**",
      "totalBallots": 1
    },
    {
      "rank": 38,
      "maskedName": "MUHA**** SUH***",
      "totalBallots": 1
    },
    {
      "rank": 39,
      "maskedName": "PO* LIA** HO**",
      "totalBallots": 1
    },
    {
      "rank": 40,
      "maskedName": "RAYM*** GO*",
      "totalBallots": 1
    },
    {
      "rank": 41,
      "maskedName": "RE* TA*",
      "totalBallots": 1
    },
    {
      "rank": 42,
      "maskedName": "RIN** PA* SIN**",
      "totalBallots": 1
    },
    {
      "rank": 43,
      "maskedName": "ROXA***",
      "totalBallots": 1
    },
    {
      "rank": 44,
      "maskedName": "RY** LE* JI* XI**",
      "totalBallots": 1
    },
    {
      "rank": 45,
      "maskedName": "SE** JI* SHE**",
      "totalBallots": 1
    },
    {
      "rank": 46,
      "maskedName": "TA* EN* YE** RAC***",
      "totalBallots": 1
    },
    {
      "rank": 47,
      "maskedName": "TA* JI** WE* CLAR****",
      "totalBallots": 1
    },
    {
      "rank": 48,
      "maskedName": "TA* MINGZH***** JOV***",
      "totalBallots": 1
    },
    {
      "rank": 49,
      "maskedName": "TE* JI* TO**",
      "totalBallots": 1
    },
    {
      "rank": 50,
      "maskedName": "TO** CH**",
      "totalBallots": 1
    },
    {
      "rank": 51,
      "maskedName": "AMA*** ON*",
      "totalBallots": 0
    },
    {
      "rank": 52,
      "maskedName": "AMA** LI* TONG***",
      "totalBallots": 0
    },
    {
      "rank": 53,
      "maskedName": "AN* JI** XU**",
      "totalBallots": 0
    },
    {
      "rank": 54,
      "maskedName": "ASH***",
      "totalBallots": 0
    },
    {
      "rank": 55,
      "maskedName": "BRAN*** AN*",
      "totalBallots": 0
    },
    {
      "rank": 56,
      "maskedName": "BRY**",
      "totalBallots": 0
    },
    {
      "rank": 57,
      "maskedName": "BRY** TA* YO** ER*",
      "totalBallots": 0
    },
    {
      "rank": 58,
      "maskedName": "CEL*** AN* SH* HU*",
      "totalBallots": 0
    },
    {
      "rank": 59,
      "maskedName": "CH** YOO** HU*",
      "totalBallots": 0
    },
    {
      "rank": 60,
      "maskedName": "CH** SE** ZH**",
      "totalBallots": 0
    },
    {
      "rank": 61,
      "maskedName": "DA** ON*",
      "totalBallots": 0
    },
    {
      "rank": 62,
      "maskedName": "DER** KO*",
      "totalBallots": 0
    },
    {
      "rank": 63,
      "maskedName": "DER** KO* JI** JI*",
      "totalBallots": 0
    },
    {
      "rank": 64,
      "maskedName": "ELL***",
      "totalBallots": 0
    },
    {
      "rank": 65,
      "maskedName": "FID** TA*",
      "totalBallots": 0
    },
    {
      "rank": 66,
      "maskedName": "GI** YA* HU*",
      "totalBallots": 0
    },
    {
      "rank": 67,
      "maskedName": "GO* JU* Z* GAV**",
      "totalBallots": 0
    },
    {
      "rank": 68,
      "maskedName": "GO* XU* Q*",
      "totalBallots": 0
    },
    {
      "rank": 69,
      "maskedName": "HO* KA* CHI**",
      "totalBallots": 0
    },
    {
      "rank": 70,
      "maskedName": "IRE** GU*",
      "totalBallots": 0
    },
    {
      "rank": 71,
      "maskedName": "IRW** HE** DI** XIA**",
      "totalBallots": 0
    },
    {
      "rank": 72,
      "maskedName": "JAL*** CH** JI* XIA**",
      "totalBallots": 0
    },
    {
      "rank": 73,
      "maskedName": "JASA**** CH** JI* XU**",
      "totalBallots": 0
    },
    {
      "rank": 74,
      "maskedName": "JAS** N*",
      "totalBallots": 0
    },
    {
      "rank": 75,
      "maskedName": "JOSEP**** TE* A* BO**",
      "totalBallots": 0
    },
    {
      "rank": 76,
      "maskedName": "JUS*** TE*",
      "totalBallots": 0
    },
    {
      "rank": 77,
      "maskedName": "KA* YA** TA*",
      "totalBallots": 0
    },
    {
      "rank": 78,
      "maskedName": "KATHE**** HE**",
      "totalBallots": 0
    },
    {
      "rank": 79,
      "maskedName": "KEL** LI* KI* YE*",
      "totalBallots": 0
    },
    {
      "rank": 80,
      "maskedName": "KEV** AN* QI* Y*",
      "totalBallots": 0
    },
    {
      "rank": 81,
      "maskedName": "KO** JU* L*",
      "totalBallots": 0
    },
    {
      "rank": 82,
      "maskedName": "KO* WE* WE*",
      "totalBallots": 0
    },
    {
      "rank": 83,
      "maskedName": "KO** O* ME*",
      "totalBallots": 0
    },
    {
      "rank": 84,
      "maskedName": "LE* WE* RE*",
      "totalBallots": 0
    },
    {
      "rank": 85,
      "maskedName": "LE* XI* Y*",
      "totalBallots": 0
    },
    {
      "rank": 86,
      "maskedName": "LI* CHRIS**** BAS**",
      "totalBallots": 0
    },
    {
      "rank": 87,
      "maskedName": "LI* L* XU** JAM**",
      "totalBallots": 0
    },
    {
      "rank": 88,
      "maskedName": "LIO*** CH** WE* HUA**",
      "totalBallots": 0
    },
    {
      "rank": 89,
      "maskedName": "MATI*** LI** YU* XU**",
      "totalBallots": 0
    },
    {
      "rank": 90,
      "maskedName": "MUHA*** NURSHA***** BI* NORA***",
      "totalBallots": 0
    },
    {
      "rank": 91,
      "maskedName": "NAD** PANW***",
      "totalBallots": 0
    },
    {
      "rank": 92,
      "maskedName": "N* G* TIO** (NA***",
      "totalBallots": 0
    },
    {
      "rank": 93,
      "maskedName": "NG** CH** KHU**",
      "totalBallots": 0
    },
    {
      "rank": 94,
      "maskedName": "NICH**** SI**",
      "totalBallots": 0
    },
    {
      "rank": 95,
      "maskedName": "NIC*** GO* L* YI**",
      "totalBallots": 0
    },
    {
      "rank": 96,
      "maskedName": "NUR** KHAIRU***** BIN** RAZ***",
      "totalBallots": 0
    },
    {
      "rank": 97,
      "maskedName": "PRIN**** DY** LE* ROG**",
      "totalBallots": 0
    },
    {
      "rank": 98,
      "maskedName": "REN**",
      "totalBallots": 0
    },
    {
      "rank": 99,
      "maskedName": "ROM*** DAN*** ETH** LUS***",
      "totalBallots": 0
    },
    {
      "rank": 100,
      "maskedName": "RY** TA*",
      "totalBallots": 0
    },
    {
      "rank": 101,
      "maskedName": "SAR** RAH**",
      "totalBallots": 0
    },
    {
      "rank": 102,
      "maskedName": "SH** KA* LI**",
      "totalBallots": 0
    },
    {
      "rank": 103,
      "maskedName": "SHREET***** PIRAS*****",
      "totalBallots": 0
    },
    {
      "rank": 104,
      "maskedName": "SHR*** BO**",
      "totalBallots": 0
    },
    {
      "rank": 105,
      "maskedName": "SN* EN* KI**",
      "totalBallots": 0
    },
    {
      "rank": 106,
      "maskedName": "SON** LE*",
      "totalBallots": 0
    },
    {
      "rank": 107,
      "maskedName": "SUWA*** ONM*** (JI**",
      "totalBallots": 0
    },
    {
      "rank": 108,
      "maskedName": "SY** MAT** MIR**",
      "totalBallots": 0
    },
    {
      "rank": 109,
      "maskedName": "TA* JI** HER**",
      "totalBallots": 0
    },
    {
      "rank": 110,
      "maskedName": "TA* WE* XU**",
      "totalBallots": 0
    },
    {
      "rank": 111,
      "maskedName": "TA* Y* X* BRAD***",
      "totalBallots": 0
    },
    {
      "rank": 112,
      "maskedName": "TA* YO* MI*",
      "totalBallots": 0
    },
    {
      "rank": 113,
      "maskedName": "TA* KA* E*",
      "totalBallots": 0
    },
    {
      "rank": 114,
      "maskedName": "TA* KA* XU**",
      "totalBallots": 0
    },
    {
      "rank": 115,
      "maskedName": "TA* KA* YA**",
      "totalBallots": 0
    },
    {
      "rank": 116,
      "maskedName": "TA* PE** KHO**",
      "totalBallots": 0
    },
    {
      "rank": 117,
      "maskedName": "TE* TZ* YA**",
      "totalBallots": 0
    },
    {
      "rank": 118,
      "maskedName": "THER*** GA* SALV**** LI*",
      "totalBallots": 0
    },
    {
      "rank": 119,
      "maskedName": "TO*",
      "totalBallots": 0
    },
    {
      "rank": 120,
      "maskedName": "WE* XIA** G*",
      "totalBallots": 0
    },
    {
      "rank": 121,
      "maskedName": "YA** PATHIRA****** YASA**** ANUR**** PATHI****",
      "totalBallots": 0
    },
    {
      "rank": 122,
      "maskedName": "YE* LA* HO**",
      "totalBallots": 0
    },
    {
      "rank": 123,
      "maskedName": "YE* LA* HU*",
      "totalBallots": 0
    },
    {
      "rank": 124,
      "maskedName": "YE* WE* QI*",
      "totalBallots": 0
    },
    {
      "rank": 125,
      "maskedName": "YE** MAN**",
      "totalBallots": 0
    },
    {
      "rank": 126,
      "maskedName": "ZI** GU*",
      "totalBallots": 0
    }
  ]
}
